[
  {
    "id": "mp_67f53507a232",
    "prompt_text": "celtic, melodic, melancholic, female vocal trance, synthwave / electro, trance, celtic, melodic, melancholic, female vocal trance, synthwave / electro, trance, electric bass guitar, electric guitar, guitar virtuoso, celtic metal, ",
    "prompt_zh": "凯尔特 (Celtic), 旋律 (Melodic), 悲伤 (Melancholic), 女声迷幻电子乐 (Female Vocal Trance), 合成器浪潮 / 电子 (Synthwave / Electro), 迷幻电子乐 (Trance), electric bass guitar, electric guitar, guitar virtuoso, 凯尔特金属 (Celtic Metal)",
    "platform": "udio",
    "genre": [
      "metal",
      "trance"
    ],
    "bpm": null,
    "key": null,
    "instruments": [
      "guitar",
      "bass",
      "synth"
    ],
    "quality_score": 7.17,
    "use_cases": [],
    "source": "mister-magpie/6cc8de34-cc9d-4a8b-8835-5bdf5784624a",
    "title": "Echoes of Desire",
    "translation_meta": {
      "title_zh": "凯尔特旋律悲伤的女声迷幻电子乐",
      "genre_tags_zh": [
        "凯尔特 (Celtic)",
        "迷幻电子乐 (Trance)",
        "合成器浪潮 (Synthwave)",
        "电子 (Electro)",
        "凯尔特金属 (Celtic Metal)"
      ],
      "mood_keywords_zh": [
        "旋律 (Melodic)",
        "悲伤 (Melancholic)"
      ],
      "translated_at": "2026-03-25T14:47:08.212726"
    }
  },
  {
    "id": "mp_a716d8c2b93f",
    "prompt_text": "\"Compose a heavy metal track inspired by a british 80s band. The song should feature galloping bass lines, twin guitar harmonies, and soaring, operatic vocals. The tempo should be fast and driving, with powerful, complex riffs and energetic drumming that includes fast double bass kicks. The guitar solos should be intricate and melodic, showcasing technical prowess with a mix of speed and emotion. Lyrically, the song should tell an epic, mythological or historical story, filled with vivid imagery and a sense of grandeur. The overall tone should be dramatic, intense, and full of energy, with a powerful and anthemic chorus.\"",
    "prompt_zh": "创作一首受80年代英国乐队启发的Heavy Metal曲目。歌曲应包含快速的[贝斯]线条、双吉他和声和高亢的歌剧式[人声]。节奏应快速且充满驱动力，包含强有力的复杂[吉他]段落和充满活力的[鼓]演奏，其中应包括快速的双踏板击打。[吉他独奏]应复杂且旋律优美，展示技术娴熟，同时融合速度和情感。歌词上，歌曲应讲述一个史诗般、神话或历史的故事，充满生动的意象和宏伟的氛围。整体基调应戏剧化、强烈且充满能量，[副歌]部分应强有力且具有颂歌般的氛围。",
    "platform": "udio",
    "genre": [
      "metal"
    ],
    "bpm": null,
    "key": null,
    "instruments": [
      "guitar",
      "bass"
    ],
    "quality_score": 7.0,
    "use_cases": [
      "gaming"
    ],
    "source": "mister-magpie/980aa5d3-8e05-4f90-a9d7-4bbb0e59a953",
    "title": "Magnus Maiden - Run for your life",
    "translation_meta": {
      "title_zh": "受80年代英国乐队启发的重金属曲目",
      "genre_tags_zh": [
        "重金属 (Heavy Metal)"
      ],
      "mood_keywords_zh": [
        "戏剧化",
        "强烈",
        "充满能量",
        "颂歌般的"
      ],
      "translated_at": "2026-03-25T14:52:01.298029"
    }
  },
  {
    "id": "mp_f10bb4cf0d36",
    "prompt_text": "a song in the key of C major, female vocals, violin, double bass,  acoustic guitars, dark, metal, uptempo, piano, melancholic, orchestral, movie, catchy, melodic, acoustic bass guitar, ",
    "prompt_zh": "一首C major调性的歌曲，女声演唱，violin，double bass，acoustic guitars，黑暗，metal，快节奏，piano，忧郁，orchestral，电影感，朗朗上口，melodic，acoustic bass guitar",
    "platform": "udio",
    "genre": [
      "metal"
    ],
    "bpm": null,
    "key": null,
    "instruments": [
      "guitar",
      "piano",
      "violin",
      "bass"
    ],
    "quality_score": 7.0,
    "use_cases": [
      "cinematic"
    ],
    "source": "mister-magpie/42930c73-0f26-4615-a423-af94fac5a135",
    "title": "Echoes of Fate 22987 Best YET use this for the next extension",
    "translation_meta": {
      "title_zh": "C大调的歌曲",
      "genre_tags_zh": [
        "金属 (Metal)",
        "管弦乐 (Orchestral)",
        "电影 (Movie)"
      ],
      "mood_keywords_zh": [
        "黑暗",
        "忧郁",
        "快节奏",
        "朗朗上口",
        "旋律"
      ],
      "translated_at": "2026-03-25T14:52:56.480815"
    }
  }
]